asap/__init__.py
asap/dataset.py
asap/task.py
asap/dataloader/__init__.py
asap/dataloader/augmentation.py
asap/dataloader/base.py
asap/dataloader/bounded.py
asap/dataloader/bw_to_data.py
asap/dataloader/peak.py
asap/dataloader/wg.py
asap/dataloader/utils/__init__.py
asap/dataloader/utils/data_bed.py
asap/dataloader/utils/data_bw.py
asap/dataloader/utils/fnv64.py
asap/dataloader/utils/io.py
asap/dataloader/utils/seq.py
asap/models/__init__.py
asap/models/convnext_cnn.py
asap/models/convnext_dcnn.py
asap/models/convnext_lstm.py
asap/models/convnext_transformer.py
asap/models/dilated_cnn.py
asap/models/load_model.py
asap/models/recurrent.py
asap/models/vanilla_cnn.py
asap/models/xlstm.py
asap/models/layers/__init__.py
asap/models/layers/convnext.py
asap/models/layers/grn.py
asap/models/layers/rope.py
asap/models/layers/rope_new.py
asap/models/layers/unmap_predictor.py
asap/snv/__init__.py
asap/snv/data_loader.py
asap/snv/filter_snvs.py
asap/snv/plot_FC_scatter.py
asap/snv/plot_PCC_vs_reads.py
asap/snv/predict.py
asap/trainer/__init__.py
asap/trainer/trainer.py
asap/utils/logger.py
asap/utils/metrics.py
asap/utils/optim.py
atac_asap-0.2.0.dist-info/LICENSE
atac_asap-0.2.0.dist-info/METADATA
atac_asap-0.2.0.dist-info/WHEEL
atac_asap-0.2.0.dist-info/top_level.txt
atac_asap-0.2.0.dist-info/RECORD
