Metadata-Version: 2.1
Name: atac-asap
Version: 0.2.0
Summary: A package for Allele-specific ATAC-seq prediction (ASAP)
Author-email: Aayush Grover <aayush.grover@inf.ethz.ch>, Till Muser <till.muser@sdsc.ethz.ch>, Liine Kasak <lkasak@student.ethz.ch>, Lin Zhang <lin.zhang@sdsc.ethz.ch>, Ekaterina Krymova <ekaterina.krymova@sdsc.ethz.ch>, Valentina Boeva <valentina.boeva@inf.ethz.ch>
License: MIT License
Project-URL: Homepage, https://github.com/BoevaLab/ASAP
Project-URL: Repository, https://github.com/BoevaLab/ASAP
Project-URL: Documentation, https://github.com/BoevaLab/ASAP/wiki
Classifier: Programming Language :: Python :: 3
Classifier: Operating System :: OS Independent
Requires-Python: >=3.8
License-File: LICENSE
Requires-Dist: antlr4-python3-runtime~=4.9.3
Requires-Dist: dacite
Requires-Dist: filelock>=3.13.1
Requires-Dist: fsspec>=2023.12.2
Requires-Dist: hydra-core~=1.3.2
Requires-Dist: importlib-metadata~=7.0.1
Requires-Dist: jinja2~=3.1.3
Requires-Dist: mpmath~=1.3.0
Requires-Dist: networkx>=3.1
Requires-Dist: numpy<2.0,>=1.12.0
Requires-Dist: omegaconf~=2.3.0
Requires-Dist: packaging>=23.2
Requires-Dist: pandas>=2.0
Requires-Dist: pillow~=10.2.0
Requires-Dist: pybigwig>=0.3.22
Requires-Dist: pyfaidx>=0.8.1.1
Requires-Dist: pysam>=0.22.0
Requires-Dist: python-dateutil~=2.8.2
Requires-Dist: pytz~=2023.3.post1
Requires-Dist: pyyaml~=6.0.1
Requires-Dist: scipy>=1.10.0
Requires-Dist: six~=1.16.0
Requires-Dist: sympy~=1.12
Requires-Dist: torch==2.1.2
Requires-Dist: torchaudio==2.1.2
Requires-Dist: torchinfo~=1.8.0
Requires-Dist: torchmetrics
Requires-Dist: torchvision==0.16.2
Requires-Dist: tqdm>=4.66.1
Requires-Dist: tzdata~=2023.4
Requires-Dist: zipp~=3.17.0
Provides-Extra: dev
Requires-Dist: pre-commit; extra == "dev"
Requires-Dist: pytest; extra == "dev"
Requires-Dist: pytest-xdist; extra == "dev"
